domino/__init__.py
domino/detect.py
domino/represent_and_analyze.py
domino/bic_minimization/__init__.py
domino/bic_minimization/binary_bic.py
domino/bic_minimization/signed_bic.py
domino/bic_minimization/weighted_bic.py
domino/ergms_solvers/__init__.py
domino/ergms_solvers/binary_solvers.py
domino/ergms_solvers/signed_solvers.py
domino/ergms_solvers/weighted_solvers.py
domino/leiden/__init__.py
domino/leiden/leiden_engine.py
domino/leiden/partitions_functions.py
domino/leiden/scoring.py
domino/utils/__init__.py
domino/utils/constants.py
domino/utils/repro.py
domino_mesoscale-0.1.0.dist-info/licenses/LICENSE
domino_mesoscale-0.1.0.dist-info/METADATA
domino_mesoscale-0.1.0.dist-info/WHEEL
domino_mesoscale-0.1.0.dist-info/top_level.txt
domino_mesoscale-0.1.0.dist-info/RECORD
