Metadata-Version: 2.4
Name: domino-mesoscale
Version: 0.1.0
Summary: DOMINO, Detection Of MesoscopIc structures via iNfOrmation criteria
Author-email: Mattia Marzi <mattia.marzi@imtlucca.it>
License: MIT License
Project-URL: Homepage, https://github.com/mattiamarzi/DOMINO
Project-URL: Repository, https://github.com/mattiamarzi/DOMINO
Keywords: networks,mesoscales,mesoscale-detection,sbm,leiden,bic
Classifier: Programming Language :: Python :: 3
Classifier: License :: OSI Approved :: MIT License
Classifier: Operating System :: OS Independent
Requires-Python: >=3.10
License-File: LICENSE
Requires-Dist: numpy>=1.23
Requires-Dist: networkx>=3.0
Requires-Dist: scipy>=1.10
Requires-Dist: numba>=0.57
Provides-Extra: viz
Requires-Dist: matplotlib>=3.7; extra == "viz"
Provides-Extra: dev
Requires-Dist: pytest>=7; extra == "dev"
Requires-Dist: ruff>=0.5; extra == "dev"
Requires-Dist: pre-commit>=3.7; extra == "dev"
Requires-Dist: build>=1.2; extra == "dev"
Requires-Dist: twine>=5; extra == "dev"
Dynamic: license-file
